{"data":{"allMarkdownRemark":{"edges":[{"node":{"frontmatter":{"title":"Continuing with materials!","date":"2019-01-09","course":"Unreal Engine: Material Concepts","courseUrl":"https://academy.unrealengine.com/Class/materials-essentials","category":"ue"},"excerpt":"Material Expressions"}},{"node":{"frontmatter":{"title":"Getting started with Materials!","date":"2019-01-08","course":"Unreal Engine: Material Concepts","courseUrl":"https://academy.unrealengine.com/Class/materials-essentials","category":"ue"},"excerpt":"Introduction, Textures, First Material, Physically Based Rendering"}},{"node":{"frontmatter":{"title":"C++ continue! or break?","date":"2019-01-07","course":"Udemy: C++ Tutorial for Complete Beginners","courseUrl":"https://www.udemy.com/free-learn-c-tutorial-beginners/","category":"cpp"},"excerpt":"break and continue, arrays, multidimensional arrays"}},{"node":{"frontmatter":{"title":"Typescript Sunday!","date":"2019-01-06","course":"FrontendMasters: Typescript","courseUrl":"https://frontendmasters.com/courses/typescript/","category":"js"},"excerpt":"Classes, Enums, Arrays & Tuples, Rest & Spread Properties, Getters & Setters"}},{"node":{"frontmatter":{"title":"C++, the journey goes on","date":"2019-01-05","course":"Udemy: C++ Tutorial for Complete Beginners","courseUrl":"https://www.udemy.com/free-learn-c-tutorial-beginners/","category":"cpp"},"excerpt":"learned conditions, about type char and bool"}},{"node":{"frontmatter":{"title":"Time Complexity","date":"2019-01-04","course":"FrontendMasters: Data Structures and Algorithms in JavaScript","courseUrl":"https://frontendmasters.com/courses/data-structures-algorithms/","category":"cs"},"excerpt":"Learned how to calculate time complexity, understanding Big-O"}},{"node":{"frontmatter":{"title":"Continue with C++","date":"2019-01-03","course":"Udemy: C++ Tutorial for Complete Beginners","courseUrl":"https://www.udemy.com/free-learn-c-tutorial-beginners/","category":"cpp"},"excerpt":"found out how laborious it is to make a string lowercase, learned about types, played around with numbers"}},{"node":{"frontmatter":{"title":"Typescript!","date":"2019-01-02","course":"FrontendMasters: Typescript","courseUrl":"https://frontendmasters.com/courses/typescript/","category":"js"},"excerpt":"Interfaces, any & never types, learned about \"species\" "}},{"node":{"frontmatter":{"title":"C++ from Zero!","date":"2019-01-02","course":"Udemy: C++ Tutorial for Complete Beginners","courseUrl":"https://www.udemy.com/free-learn-c-tutorial-beginners/","category":"cpp"},"excerpt":"Setup C++ Enviroment, created Hello World, played around with text outputting"}},{"node":{"frontmatter":{"title":"Finished materials!","date":"2019-01-10","course":"Unreal Engine: Material Concepts","courseUrl":"https://academy.unrealengine.com/Class/materials-essentials","category":"ue"},"excerpt":"Material Inputs, Material Properties"}},{"node":{"frontmatter":{"title":"Getting started with Typescript!","date":"2019-01-01","course":"FrontendMasters: Typescript","courseUrl":"https://frontendmasters.com/courses/typescript/","category":"js"},"excerpt":"Implicit Typing, Explicit Typing, Object Shapes"}}]}},"pageContext":{}}